sgnligo/__init__.py
sgnligo/_version.py
sgnligo/estimate.py
sgnligo/kernels.py
sgnligo/psd.py
sgnligo/base/__init__.py
sgnligo/base/utils.py
sgnligo/bin/__init__.py
sgnligo/bin/coinc_to_html.py
sgnligo/bin/fake_frames.py
sgnligo/bin/gwistat.py
sgnligo/bin/ll_dq.py
sgnligo/bin/plot_psd.py
sgnligo/gwpy/__init__.py
sgnligo/gwpy/converters.py
sgnligo/gwpy/sinks/__init__.py
sgnligo/gwpy/sinks/plot_sink.py
sgnligo/gwpy/sinks/timeseries_sink.py
sgnligo/gwpy/sources/__init__.py
sgnligo/gwpy/sources/timeseries_source.py
sgnligo/gwpy/transforms/__init__.py
sgnligo/gwpy/transforms/filter.py
sgnligo/gwpy/transforms/qtransform.py
sgnligo/gwpy/transforms/spectrogram.py
sgnligo/plots/psd.py
sgnligo/plots/util.py
sgnligo/sinks/__init__.py
sgnligo/sinks/coinc_xml_sink.py
sgnligo/sinks/frame_sink.py
sgnligo/sinks/influx_sink.py
sgnligo/sinks/kafka_sink.py
sgnligo/sinks/psd_sink.py
sgnligo/sources/__init__.py
sgnligo/sources/datasource.py
sgnligo/sources/devshmsrc.py
sgnligo/sources/framecachesrc.py
sgnligo/sources/gwdata_noise_source.py
sgnligo/sources/gwosc.py
sgnligo/sources/injected_noise_source.py
sgnligo/sources/mock_event_source.py
sgnligo/sources/sim_inspiral_source.py
sgnligo/transforms/__init__.py
sgnligo/transforms/bit_mask.py
sgnligo/transforms/condition.py
sgnligo/transforms/horizon.py
sgnligo/transforms/latency.py
sgnligo/transforms/whiten.py
sgn_ligo-0.2.0.dist-info/METADATA
sgn_ligo-0.2.0.dist-info/WHEEL
sgn_ligo-0.2.0.dist-info/entry_points.txt
sgn_ligo-0.2.0.dist-info/top_level.txt
sgn_ligo-0.2.0.dist-info/RECORD
