Metadata-Version: 2.4
Name: sgn-ligo
Version: 0.2.0
Summary: LIGO Extensions for the SGN Framework
Author-email: Chad Hanna <crh184@psu.edu>, Yun-Jing Huang <yzh5436@psu.edu>, James Kennington <jmk7376@psu.edu>
License-Expression: MPL-2.0
Project-URL: Homepage, https://git.ligo.org/greg/sgn-ligo
Project-URL: Documentation, https://docs.ligo.org/greg/sgn-ligo
Project-URL: Issues, https://git.ligo.org/greg/sgn-ligo/issues
Classifier: Programming Language :: Python :: 3
Classifier: Operating System :: OS Independent
Requires-Python: >=3.10
Requires-Dist: confluent-kafka
Requires-Dist: gwpy
Requires-Dist: h5py
Requires-Dist: igwn-ligolw
Requires-Dist: igwn-segments
Requires-Dist: lalsuite>=7.26
Requires-Dist: ligo-scald
Requires-Dist: scipy<1.17
Requires-Dist: sgn>=0.5
Requires-Dist: sgn-arrakis
Requires-Dist: sgn-ts>=0.5
Requires-Dist: zlw
Requires-Dist: sympy
Requires-Dist: watchdog
Requires-Dist: pandas
Provides-Extra: test
Requires-Dist: pytest; extra == "test"
Requires-Dist: pytest-cov; extra == "test"
Requires-Dist: pytest-freezer; extra == "test"
Requires-Dist: pytest-markdown-docs; extra == "test"
Provides-Extra: docs
Requires-Dist: mkdocs; extra == "docs"
Requires-Dist: mkdocstrings; extra == "docs"
Requires-Dist: mkdocstrings-python; extra == "docs"
Requires-Dist: mkdocs-material; extra == "docs"
Requires-Dist: pymdown-extensions; extra == "docs"
Provides-Extra: lint
Requires-Dist: black; extra == "lint"
Requires-Dist: flake8; extra == "lint"
Requires-Dist: flake8-bandit; extra == "lint"
Requires-Dist: flake8-black; extra == "lint"
Requires-Dist: flake8-bugbear; extra == "lint"
Requires-Dist: flake8-future-annotations; extra == "lint"
Requires-Dist: flake8-isort; extra == "lint"
Requires-Dist: flake8-logging-format; extra == "lint"
Requires-Dist: flake8-pyproject; extra == "lint"
Requires-Dist: isort; extra == "lint"
Requires-Dist: mypy; extra == "lint"
Requires-Dist: mypy-extensions; extra == "lint"
Provides-Extra: dev
Requires-Dist: sgn-ligo[docs]; extra == "dev"
Requires-Dist: sgn-ligo[lint]; extra == "dev"
Requires-Dist: sgn-ligo[test]; extra == "dev"
